LICENSE
README.md
setup.py
pysyncq/__init__.py
pysyncq/header.py
pysyncq/pysyncq.py
pysyncq.egg-info/PKG-INFO
pysyncq.egg-info/SOURCES.txt
pysyncq.egg-info/dependency_links.txt
pysyncq.egg-info/not-zip-safe
pysyncq.egg-info/top_level.txt
pysyncq/tests/__init__.py
pysyncq/tests/benchmark.py
pysyncq/tests/demo.py
pysyncq/tests/teststart.py