Metadata-Version: 2.1
Name: pysyncq
Version: 0.0.1
Summary: Coordinate state & timing of multiple processes.
Home-page: https://github.com/jsdpag/pysyncq
Author: Jackson Smith
License: GPL
License-File: LICENSE
